mandelbrot_viewer/__init__.py
mandelbrot_viewer/mandelbrot_calculator.py
mandelbrot_viewer/mandelbrot_viewer_main.py
mandelbrot_viewer/mandelbrotwiever.kv
mandelbrot_viewer/remote_server.py
mandelbrot_viewer/shared_memory_handler.py
mandelbrot_viewer/ti_bigfloat_compute_server.py
mandelbrot_viewer-0.1.14.dist-info/METADATA
mandelbrot_viewer-0.1.14.dist-info/WHEEL
mandelbrot_viewer-0.1.14.dist-info/entry_points.txt
mandelbrot_viewer-0.1.14.dist-info/top_level.txt
mandelbrot_viewer-0.1.14.dist-info/RECORD
