Metadata-Version: 2.4
Name: mandelbrot-viewer
Version: 0.1.14
Summary: An arbitrary precision GPU accelerated mandelbrot set viewer buit with kivy and taichi.
Author-email: Balázs Szalai <balazs.backup.2@gmail.com>
Project-URL: Homepage, https://github.com/balazs-szalai/mandelbrot-set-viewer
Requires-Python: >=3.9
Requires-Dist: cython
Requires-Dist: taichi-big-float>=0.1.3
Requires-Dist: kivy
Requires-Dist: sympy
Requires-Dist: matplotlib
Requires-Dist: numpy
Requires-Dist: opencv-python
